pyproject_fmt_rust-1.2.1.dist-info/METADATA
pyproject_fmt_rust-1.2.1.dist-info/WHEEL
pyproject_fmt_rust-1.2.1.dist-info/licenses/LICENSE.txt
pyproject_fmt_rust.libs/libgcc_s-1e52349c.so.1
pyproject_fmt_rust/__init__.py
pyproject_fmt_rust/_lib.pyi
pyproject_fmt_rust/py.typed
pyproject_fmt_rust/_lib.abi3.so
pyproject_fmt_rust-1.2.1.dist-info/RECORD
