Metadata-Version: 2.3
Name: pyproject-fmt-rust
Version: 1.2.1
Classifier: License :: OSI Approved :: MIT License
Classifier: Operating System :: OS Independent
Classifier: Programming Language :: Python
Classifier: Programming Language :: Python :: 3 :: Only
Classifier: Programming Language :: Python :: 3.9
Classifier: Programming Language :: Python :: 3.10
Classifier: Programming Language :: Python :: 3.11
Classifier: Programming Language :: Python :: 3.12
Classifier: Programming Language :: Python :: 3.13
Requires-Dist: covdefaults >=2.3 ; extra == 'test'
Requires-Dist: pytest >=8.3.2 ; extra == 'test'
Requires-Dist: pytest-cov >=5 ; extra == 'test'
Provides-Extra: test
License-File: LICENSE.txt
Summary: Format your pyproject.toml file
Keywords: format,pyproject
Author-email: Bernat Gabor <gaborjbernat@gmail.com>
License: MIT
Requires-Python: >=3.9
Project-URL: Bug Tracker, https://github.com/tox-dev/pyproject-fmt-rust/issues
Project-URL: Changelog, https://github.com/tox-dev/pyproject-fmt-rust/releases
Project-URL: Documentation, https://github.com/tox-dev/pyproject-fmt-rust/
Project-URL: Source Code, https://github.com/tox-dev/pyproject-fmt-rust
